{
  "month": "2024-12",
  "postCount": 16,
  "posts": [
    {
      "id": "1735305617-66",
      "media": [
        {
          "uri": "images/posts/202412/471641166_1752042755596248_8565080767431437572_n_18030906929208522.jpg",
          "creation_timestamp": 1735305616,
          "alt": "P.willinckii anne"
        },
        {
          "uri": "images/posts/202412/471816304_607172551769638_1468484495831846053_n_18368530600139594.jpg",
          "creation_timestamp": 1735305616,
          "alt": "P.willinckii anne"
        }
      ],
      "title": "P.willinckii anne\nfrom @tmk_plants \nJTBã§ç®¡çãã¦ããå¿ãªããèª¿å­ãä¸ãã£ã¦ãæ°ãããã\n\n#ãã«ã¯ã·ã\n#ãã«ã¯ã·ãã®ããæ®ãã \n#ãã«ã¯ã·ãå¥½ããªäººã¨ç¹ãããã \n#ãã«ã¯ã·ãå¥½ãã¨ç¹ãããã \n#è¦³èæ¤ç© \n#è¦³èæ¤ç©ã®ããæ®ãã \n#è¦³èæ¤ç©ã¤ã³ããªã¢\n#platycerium \n#willinckii \n#platyceriumwillinckii \n#ç³è§ç¾æ­¯\n\n#ã¸ãµã¯ãã¢ã³",
      "creation_timestamp": 1735305617,
      "hashtags": [
        "#ãã«ã¯ã·ã",
        "#ãã«ã¯ã·ãã®ããæ®ãã",
        "#ãã«ã¯ã·ãå¥½ããªäººã¨ç¹ãããã",
        "#ãã«ã¯ã·ãå¥½ãã¨ç¹ãããã",
        "#è¦³èæ¤ç©",
        "#è¦³èæ¤ç©ã®ããæ®ãã",
        "#è¦³èæ¤ç©ã¤ã³ããªã¢",
        "#platycerium",
        "#willinckii",
        "#platyceriumwillinckii",
        "#ç³è§ç¾æ­¯",
        "#ã¸ãµã¯ãã¢ã³"
      ],
      "year": 2024,
      "month": 12,
      "day": 27
    },
    {
      "id": "1735219432-67",
      "media": [
        {
          "uri": "images/posts/202412/471880863_1738209733579000_1867557501631052001_n_18053620400069398.jpg",
          "creation_timestamp": 1735219431,
          "alt": "Platycerium ridleyi nano"
        },
        {
          "uri": "images/posts/202412/471672047_8932575106809847_6208961782417966420_n_18297694924229408.jpg",
          "creation_timestamp": 1735219431,
          "alt": "Platycerium ridleyi nano"
        }
      ],
      "title": "Platycerium ridleyi nano\nfrom @katsu_hibino \nãããããããã¹ã¿ãã°ãã¼ã³ãã¡ã¼ã³ã¡ãããã¤ã§ããã\n\n#ãã«ã¯ã·ã \n#ãã«ã¯ã·ãã®ããæ®ãã \n#ãã«ã¯ã·ãåå¿è \n#ãã«ã¯ã·ãå¥½ããªäººã¨ç¹ãããã \n#ãã«ã¯ã·ããªãã¬ã¤ \n#ãªãã¬ã¤ \n#platycerium \n#platyceriumridleyi\n#ã¸ãµã¯ããã",
      "creation_timestamp": 1735219432,
      "hashtags": [
        "#ãã«ã¯ã·ã",
        "#ãã«ã¯ã·ãã®ããæ®ãã",
        "#ãã«ã¯ã·ãåå¿è",
        "#ãã«ã¯ã·ãå¥½ããªäººã¨ç¹ãããã",
        "#ãã«ã¯ã·ããªãã¬ã¤",
        "#ãªãã¬ã¤",
        "#platycerium",
        "#platyceriumridleyi",
        "#ã¸ãµã¯ããã"
      ],
      "year": 2024,
      "month": 12,
      "day": 26
    },
    {
      "id": "1735013223-68",
      "media": [
        {
          "uri": "images/posts/202412/471622861_1344094143430218_1368378228477412596_n_18007523117694735.jpg",
          "creation_timestamp": 1735013221,
          "alt": "P.willinckii moonlight"
        },
        {
          "uri": "images/posts/202412/471289017_517502521326662_3075791020491120131_n_17875650498144954.jpg",
          "creation_timestamp": 1735013222,
          "alt": "P.willinckii moonlight"
        },
        {
          "uri": "images/posts/202412/471540713_10039320859417166_2789753965957092500_n_18006963752692297.jpg",
          "creation_timestamp": 1735013221,
          "alt": "P.willinckii moonlight"
        },
        {
          "uri": "images/posts/202412/471643360_1977728806040565_2071392569063140520_n_17864789085290841.jpg",
          "creation_timestamp": 1735013221,
          "alt": "P.willinckii moonlight"
        }
      ],
      "title": "P.willinckii moonlight#PN\nfrom @katsu_hibino \nãã£ã±ç´°èã¯ããã§ããª\n\n#æ¨¹ç¥­2023spring \n#ãã«ã¯ã·ã\n#ãã«ã¯ã·ãã®ããæ®ãã \n#ãã«ã¯ã·ãå¥½ããªäººã¨ç¹ãããã \n#ãã«ã¯ã·ãå¥½ãã¨ç¹ãããã \n#è¦³èæ¤ç© \n#è¦³èæ¤ç©ã®ããæ®ãã \n#è¦³èæ¤ç©ã¤ã³ããªã¢\n#platycerium \n#willinckii \n#platyceriumwillinckii \n#ç³è§ç¾æ­¯\n#ã¸ãµã¯ãã ã¼ã³ã©ã¤ã1",
      "creation_timestamp": 1735013223,
      "hashtags": [
        "#pn",
        "#æ¨¹ç¥­2023spring",
        "#ãã«ã¯ã·ã",
        "#ãã«ã¯ã·ãã®ããæ®ãã",
        "#ãã«ã¯ã·ãå¥½ããªäººã¨ç¹ãããã",
        "#ãã«ã¯ã·ãå¥½ãã¨ç¹ãããã",
        "#è¦³èæ¤ç©",
        "#è¦³èæ¤ç©ã®ããæ®ãã",
        "#è¦³èæ¤ç©ã¤ã³ããªã¢",
        "#platycerium",
        "#willinckii",
        "#platyceriumwillinckii",
        "#ç³è§ç¾æ­¯",
        "#ã¸ãµã¯ãã"
      ],
      "year": 2024,
      "month": 12,
      "day": 24
    },
    {
      "id": "1734955467-69",
      "media": [
        {
          "uri": "images/posts/202412/471428800_546950911498975_2745991781980386679_n_18020593166635013.jpg",
          "creation_timestamp": 1734955466,
          "alt": "P.hillii has"
        },
        {
          "uri": "images/posts/202412/470951549_1308937113790950_364069091974968020_n_18114370213381988.jpg",
          "creation_timestamp": 1734955466,
          "alt": "P.hillii has"
        },
        {
          "uri": "images/posts/202412/471389910_1247833813151968_1475821390469610390_n_17989563350758516.jpg",
          "creation_timestamp": 1734955466,
          "alt": "P.hillii has"
        },
        {
          "uri": "images/posts/202412/471442602_859646816122084_4438418635207953165_n_18262993795267411.jpg",
          "creation_timestamp": 1734955466,
          "alt": "P.hillii has"
        }
      ],
      "title": "P.hillii has\nãã®æ ªã¯ãã®æãä¸éç³ä¼ä¼é·å¼æ±æµ·ç³ä¼å¯ä¼é·ã§ãããã @zutto_kin æ°ãããããããããã®ã«ãªãã¾ãã\næ¬ä¼¼è²¯æ°´èã®ããããªã®ããé¦æãã®æ°éãä»ã®ã¨ããããã¾ãããCCOã¹ã¿ã¤ã«ã§ãã\n\n#ãã«ã¯ã·ã \n#ãã«ã¯ã·ãã®ããæ®ãã \n#ãã«ã¯ã·ãæ®åå§å¡ä¼ \n#ãã«ã¯ã·ãåå¿è \n#ãã«ã¯ã·ãå¥½ããªäººã¨ç¹ãããã\n#platyceriumhillii \n#ãã«ã¯ã·ãããªã¼ \n\n#ã¸ãµã¯ããã¹",
      "creation_timestamp": 1734955467,
      "hashtags": [
        "#ãã«ã¯ã·ã",
        "#ãã«ã¯ã·ãã®ããæ®ãã",
        "#ãã«ã¯ã·ãæ®åå§å¡ä¼",
        "#ãã«ã¯ã·ãåå¿è",
        "#ãã«ã¯ã·ãå¥½ããªäººã¨ç¹ãããã",
        "#platyceriumhillii",
        "#ãã«ã¯ã·ãããªã¼",
        "#ã¸ãµã¯ããã¹"
      ],
      "year": 2024,
      "month": 12,
      "day": 23
    },
    {
      "id": "1734866139-70",
      "media": [
        {
          "uri": "images/posts/202412/470917243_1119013542992408_6417999858865202815_n_17893356696130925.jpg",
          "creation_timestamp": 1734866138,
          "alt": "P.willinckii tobari"
        },
        {
          "uri": "images/posts/202412/470913598_879097330762866_1567579270211602664_n_17950158305877395.jpg",
          "creation_timestamp": 1734866138,
          "alt": "P.willinckii tobari"
        }
      ],
      "title": "P.willinckii tobari \nfrom @pine.field.garage \nãªããªãåããªãã£ããã©ããã£ã¨è²¯æ°´èãåºã¦ãã¾ããã\nããã§åã¤ãã\n\n#ãã«ã¯ã·ã \n#ãã«ã¯ã·ãã®ããæ®ãã \n#ãã«ã¯ã·ãæ¿ä» \n#ãã«ã¯ã·ãã¦ã£ãªã³ã­ã¼ \n#ã¦ã£ãªã³ã­ã¼ \n#willinckii \n#willinckiiå \n#platyceriumwillinckii \n\n#ã¸ãµã¯ããããª",
      "creation_timestamp": 1734866139,
      "hashtags": [
        "#ãã«ã¯ã·ã",
        "#ãã«ã¯ã·ãã®ããæ®ãã",
        "#ãã«ã¯ã·ãæ¿ä»",
        "#ãã«ã¯ã·ãã¦ã£ãªã³ã­ã¼",
        "#ã¦ã£ãªã³ã­ã¼",
        "#willinckii",
        "#willinckiiå",
        "#platyceriumwillinckii",
        "#ã¸ãµã¯ããããª"
      ],
      "year": 2024,
      "month": 12,
      "day": 22
    },
    {
      "id": "1734749388-71",
      "media": [
        {
          "uri": "images/posts/202412/471298449_1332930044557094_329024950240621103_n_18072117673646804.jpg",
          "creation_timestamp": 1734749387,
          "alt": "P.coronarium"
        },
        {
          "uri": "images/posts/202412/470952872_954247933290746_3398263352778729088_n_18026047847625220.jpg",
          "creation_timestamp": 1734749387,
          "alt": "P.coronarium"
        },
        {
          "uri": "images/posts/202412/470901822_1324079619028613_5907051032545244371_n_18051071960494351.jpg",
          "creation_timestamp": 1734749387,
          "alt": "P.coronarium"
        }
      ],
      "title": "P.coronarium \nfrom @katsu_hibino \næ¥ã¯ããã¼ã®\nã³ã­ãã¯ã»ãã°\n\n#ãã«ã¯ã·ã \n#ãã«ã¯ã·ãã®ããæ®ãã \n#ãã«ã¯ã·ãå¥½ããªäººã¨ç¹ãããã \n#ãã«ã¯ã·ãå¥½ãã¨ç¹ãããã \n#ãã«ã¯ã·ãã³ã­ããªã¦ã  \n#platyceriumcoronarium\n\n#ã¸ãµã¯ãã³ã­ã",
      "creation_timestamp": 1734749388,
      "hashtags": [
        "#ãã«ã¯ã·ã",
        "#ãã«ã¯ã·ãã®ããæ®ãã",
        "#ãã«ã¯ã·ãå¥½ããªäººã¨ç¹ãããã",
        "#ãã«ã¯ã·ãå¥½ãã¨ç¹ãããã",
        "#ãã«ã¯ã·ãã³ã­ããªã¦ã",
        "#platyceriumcoronarium",
        "#ã¸ãµã¯ãã³ã­ã"
      ],
      "year": 2024,
      "month": 12,
      "day": 21
    },
    {
      "id": "1734693804-72",
      "media": [
        {
          "uri": "images/posts/202412/470917424_1269123450984983_2027869900232975217_n_18025989611288132.jpg",
          "creation_timestamp": 1734693803,
          "alt": "P.willinckii vanorn"
        },
        {
          "uri": "images/posts/202412/470917472_861504869244132_7149065752246814482_n_18078895771600996.jpg",
          "creation_timestamp": 1734693803,
          "alt": "P.willinckii vanorn"
        }
      ],
      "title": "P.willinckii vanorn \nå¦ãããªé°å²æ°ã\nããã¦ãã­ãã«ã¼ã³ã®èãããæ¡ããã\n\n#ãã«ã¯ã·ã \n#ãã«ã¯ã·ãã®ããæ®ãã \n#ãã«ã¯ã·ãæ¿ä» \n#ãã«ã¯ã·ãã¦ã£ãªã³ã­ã¼ \n#ã¦ã£ãªã³ã­ã¼ \n#willinckii \n#willinckiiå \n#platyceriumwillinckii \n\n#ã¸ãµã¯ãããã³",
      "creation_timestamp": 1734693804,
      "hashtags": [
        "#ãã«ã¯ã·ã",
        "#ãã«ã¯ã·ãã®ããæ®ãã",
        "#ãã«ã¯ã·ãæ¿ä»",
        "#ãã«ã¯ã·ãã¦ã£ãªã³ã­ã¼",
        "#ã¦ã£ãªã³ã­ã¼",
        "#willinckii",
        "#willinckiiå",
        "#platyceriumwillinckii",
        "#ã¸ãµã¯ãããã³"
      ],
      "year": 2024,
      "month": 12,
      "day": 20
    },
    {
      "id": "1734608099-73",
      "media": [
        {
          "uri": "images/posts/202412/470901356_559883406952698_4322999099266708512_n_18315547759166032.jpg",
          "creation_timestamp": 1734608097,
          "alt": "P.willinckii winnie"
        },
        {
          "uri": "images/posts/202412/470902386_3427632487369021_6321579670604626663_n_17904395130082296.jpg",
          "creation_timestamp": 1734608097,
          "alt": "P.willinckii winnie"
        },
        {
          "uri": "images/posts/202412/470917716_1129602728732858_1871596027327385078_n_18040071563041126.jpg",
          "creation_timestamp": 1734608097,
          "alt": "P.willinckii winnie"
        }
      ],
      "title": "P.willinckii winnie \nfrom @big_bell.plants_aqua \nä¸é¨åèå¢ãããã°ã¡ã³ã\nå¢ããã¤ãã¦ã¾ããã¾ããï¼\n\n#ãã«ã¯ã·ã \n#ãã«ã¯ã·ãã®ããæ®ãã \n#ãã«ã¯ã·ãæ¿ä» \n#ãã«ã¯ã·ãã¦ã£ãªã³ã­ã¼ \n#ã¦ã£ãªã³ã­ã¼ \n#willinckii \n#willinckiiå \n#platyceriumwillinckii \n#æ¥æ¬é»çè²æçµå \n\n#ã¸ãµã¯ãã¦ã£ãã¼",
      "creation_timestamp": 1734608099,
      "hashtags": [
        "#ãã«ã¯ã·ã",
        "#ãã«ã¯ã·ãã®ããæ®ãã",
        "#ãã«ã¯ã·ãæ¿ä»",
        "#ãã«ã¯ã·ãã¦ã£ãªã³ã­ã¼",
        "#ã¦ã£ãªã³ã­ã¼",
        "#willinckii",
        "#willinckiiå",
        "#platyceriumwillinckii",
        "#æ¥æ¬é»çè²æçµå",
        "#ã¸ãµã¯ãã¦ã£ãã¼"
      ],
      "year": 2024,
      "month": 12,
      "day": 19
    },
    {
      "id": "1734529830-74",
      "media": [
        {
          "uri": "images/posts/202412/470761623_1526705017988400_3946804025693880306_n_17978880218646934.jpg",
          "creation_timestamp": 1734529828,
          "alt": "P.willinckii anne"
        },
        {
          "uri": "images/posts/202412/470809166_1105990367640144_2818270193344430482_n_18049422443038536.jpg",
          "creation_timestamp": 1734529828,
          "alt": "P.willinckii anne"
        }
      ],
      "title": "P.willinckii anne\nfrom @tmk_plants \nãã¯ãJTBã§ç®¡çãã¦ããã®æ¹ãæé·æ©ãã\n\n#ãã«ã¯ã·ã\n#ãã«ã¯ã·ãã®ããæ®ãã \n#ãã«ã¯ã·ãå¥½ããªäººã¨ç¹ãããã \n#ãã«ã¯ã·ãå¥½ãã¨ç¹ãããã \n#è¦³èæ¤ç© \n#è¦³èæ¤ç©ã®ããæ®ãã \n#è¦³èæ¤ç©ã¤ã³ããªã¢\n#platycerium \n#willinckii \n#platyceriumwillinckii \n#ç³è§ç¾æ­¯\n\n#ã¸ãµã¯ãã¢ã³",
      "creation_timestamp": 1734529830,
      "hashtags": [
        "#ãã«ã¯ã·ã",
        "#ãã«ã¯ã·ãã®ããæ®ãã",
        "#ãã«ã¯ã·ãå¥½ããªäººã¨ç¹ãããã",
        "#ãã«ã¯ã·ãå¥½ãã¨ç¹ãããã",
        "#è¦³èæ¤ç©",
        "#è¦³èæ¤ç©ã®ããæ®ãã",
        "#è¦³èæ¤ç©ã¤ã³ããªã¢",
        "#platycerium",
        "#willinckii",
        "#platyceriumwillinckii",
        "#ç³è§ç¾æ­¯",
        "#ã¸ãµã¯ãã¢ã³"
      ],
      "year": 2024,
      "month": 12,
      "day": 18
    },
    {
      "id": "1734526734-75",
      "media": [
        {
          "uri": "images/posts/202412/470794257_2034135710436152_2044256096052597235_n_18050941286055859.jpg",
          "creation_timestamp": 1734526733,
          "alt": "P.willinckii gabriel"
        },
        {
          "uri": "images/posts/202412/470748416_1560860101236788_5856022488391962631_n_18071171143660558.jpg",
          "creation_timestamp": 1734526733,
          "alt": "P.willinckii gabriel"
        },
        {
          "uri": "images/posts/202412/470675629_1105330944578383_7130657107256007237_n_18085298539545804.jpg",
          "creation_timestamp": 1734526733,
          "alt": "P.willinckii gabriel"
        }
      ],
      "title": "P.willinckii gabriel \nfrom @iggy421 \nä»ã®ã¨ããç´ ç´ã«è²ã£ã¦ã¾ãã\nã¡ãã£ã¨ã ãã«ã¼ã«ããå¯æããã¤ã§ãã\n\n#ãã«ã¯ã·ã \n#ãã«ã¯ã·ãã®ããæ®ãã \n#ãã«ã¯ã·ãæ®åå§å¡ä¼ \n#ãã«ã¯ã·ãå¥½ããªäººã¨ç¹ãããã \n#ãã«ã¯ã·ãå¥½ããªäººã¨ç¹ãããã \n#platycerium \n#platyceriumwillinckii \n#willinckii\n\n#ã¸ãµã¯ãã¬ããªã¨ã«",
      "creation_timestamp": 1734526734,
      "hashtags": [
        "#ãã«ã¯ã·ã",
        "#ãã«ã¯ã·ãã®ããæ®ãã",
        "#ãã«ã¯ã·ãæ®åå§å¡ä¼",
        "#ãã«ã¯ã·ãå¥½ããªäººã¨ç¹ãããã",
        "#ãã«ã¯ã·ãå¥½ããªäººã¨ç¹ãããã",
        "#platycerium",
        "#platyceriumwillinckii",
        "#willinckii",
        "#ã¸ãµã¯ãã¬ããªã¨ã«"
      ],
      "year": 2024,
      "month": 12,
      "day": 18
    },
    {
      "id": "1734439513-76",
      "media": [
        {
          "uri": "images/posts/202412/470743052_387877477744503_7183286593670754501_n_17940985676929675.jpg",
          "creation_timestamp": 1734439512,
          "alt": "P.veitchii x coronarium"
        },
        {
          "uri": "images/posts/202412/470495769_929943732665962_6437168906187655185_n_18066168724695006.jpg",
          "creation_timestamp": 1734439512,
          "alt": "P.veitchii x coronarium"
        }
      ],
      "title": "P.veitchii x coronarium \nfrom @katsu_hibino \nãªããªãé¢ç½ããã«ã¯ã§ããè²ã¦ã¦ãäººè¦ãäºãªãã\n\n#ãã«ã¯ã·ã \n#ãã«ã¯ã·ãã®ããæ®ãã \n#ãã«ã¯ã·ãå¥½ããªäººã¨ç¹ãããã \n#ãã«ã¯ã·ãå¥½ãã¨ç¹ãããã \n#platyceriumveitchii \n#platyceriumcoronarium \n#è¦³èæ¤ç© \n#è¦³èæ¤ç©ã®ããæ®ãã \n#è¦³èæ¤ç©ã¤ã³ããªã¢\n\n#ã¸ãµã¯ããã¤ãã³ã­ã",
      "creation_timestamp": 1734439513,
      "hashtags": [
        "#ãã«ã¯ã·ã",
        "#ãã«ã¯ã·ãã®ããæ®ãã",
        "#ãã«ã¯ã·ãå¥½ããªäººã¨ç¹ãããã",
        "#ãã«ã¯ã·ãå¥½ãã¨ç¹ãããã",
        "#platyceriumveitchii",
        "#platyceriumcoronarium",
        "#è¦³èæ¤ç©",
        "#è¦³èæ¤ç©ã®ããæ®ãã",
        "#è¦³èæ¤ç©ã¤ã³ããªã¢",
        "#ã¸ãµã¯ããã¤ãã³ã­ã"
      ],
      "year": 2024,
      "month": 12,
      "day": 17
    },
    {
      "id": "1733536321-77",
      "media": [
        {
          "uri": "images/posts/202412/469694057_1038230467993009_5868421275288562876_n_18027939251228731.jpg",
          "creation_timestamp": 1733536320,
          "alt": "P.willinckii moonlight"
        },
        {
          "uri": "images/posts/202412/469609084_899905245637087_6129702734275945738_n_18191220688306149.jpg",
          "creation_timestamp": 1733536320,
          "alt": "P.willinckii moonlight"
        }
      ],
      "title": "P.willinckii moonlight#PN\nfrom @katsu_hibino \nãã­ãã­ã¢ã²ã¤ã³\n\n#æ¨¹ç¥­2023spring \n#ãã«ã¯ã·ã\n#ãã«ã¯ã·ãã®ããæ®ãã \n#ãã«ã¯ã·ãå¥½ããªäººã¨ç¹ãããã \n#ãã«ã¯ã·ãå¥½ãã¨ç¹ãããã \n#è¦³èæ¤ç© \n#è¦³èæ¤ç©ã®ããæ®ãã \n#è¦³èæ¤ç©ã¤ã³ããªã¢\n#platycerium \n#willinckii \n#platyceriumwillinckii \n#ç³è§ç¾æ­¯\n#ã¸ãµã¯ãã ã¼ã³ã©ã¤ã1",
      "creation_timestamp": 1733536321,
      "hashtags": [
        "#pn",
        "#æ¨¹ç¥­2023spring",
        "#ãã«ã¯ã·ã",
        "#ãã«ã¯ã·ãã®ããæ®ãã",
        "#ãã«ã¯ã·ãå¥½ããªäººã¨ç¹ãããã",
        "#ãã«ã¯ã·ãå¥½ãã¨ç¹ãããã",
        "#è¦³èæ¤ç©",
        "#è¦³èæ¤ç©ã®ããæ®ãã",
        "#è¦³èæ¤ç©ã¤ã³ããªã¢",
        "#platycerium",
        "#willinckii",
        "#platyceriumwillinckii",
        "#ç³è§ç¾æ­¯",
        "#ã¸ãµã¯ãã"
      ],
      "year": 2024,
      "month": 12,
      "day": 7
    },
    {
      "id": "1733398559-78",
      "media": [
        {
          "uri": "images/posts/202412/469497893_590164113526064_2023026991285760885_n_17898091959061359.jpg",
          "creation_timestamp": 1733398557,
          "alt": "P.willinckii anne"
        },
        {
          "uri": "images/posts/202412/469483800_3943844412501681_6148464983207953026_n_18361921837185069.jpg",
          "creation_timestamp": 1733398557,
          "alt": "P.willinckii anne"
        }
      ],
      "title": "P.willinckii anne\nfrom @tmk_plants \nJTBã§ç®¡çãã¦ããå¿ãªããèª¿å­ãä¸ãã£ã¦ãæ°ãããã\n\n#ãã«ã¯ã·ã\n#ãã«ã¯ã·ãã®ããæ®ãã \n#ãã«ã¯ã·ãå¥½ããªäººã¨ç¹ãããã \n#ãã«ã¯ã·ãå¥½ãã¨ç¹ãããã \n#è¦³èæ¤ç© \n#è¦³èæ¤ç©ã®ããæ®ãã \n#è¦³èæ¤ç©ã¤ã³ããªã¢\n#platycerium \n#willinckii \n#platyceriumwillinckii \n#ç³è§ç¾æ­¯\n\n#ã¸ãµã¯ãã¢ã³",
      "creation_timestamp": 1733398559,
      "hashtags": [
        "#ãã«ã¯ã·ã",
        "#ãã«ã¯ã·ãã®ããæ®ãã",
        "#ãã«ã¯ã·ãå¥½ããªäººã¨ç¹ãããã",
        "#ãã«ã¯ã·ãå¥½ãã¨ç¹ãããã",
        "#è¦³èæ¤ç©",
        "#è¦³èæ¤ç©ã®ããæ®ãã",
        "#è¦³èæ¤ç©ã¤ã³ããªã¢",
        "#platycerium",
        "#willinckii",
        "#platyceriumwillinckii",
        "#ç³è§ç¾æ­¯",
        "#ã¸ãµã¯ãã¢ã³"
      ],
      "year": 2024,
      "month": 12,
      "day": 5
    },
    {
      "id": "1733370778-79",
      "media": [
        {
          "uri": "images/posts/202412/469487724_474290748570757_367912393029607359_n_17884701909169103.jpg",
          "creation_timestamp": 1733370776,
          "alt": "P.willinckii æåçªå"
        },
        {
          "uri": "images/posts/202412/469491549_1279486369927348_2522253167883313410_n_17893903464038654.jpg",
          "creation_timestamp": 1733370776,
          "alt": "P.willinckii æåçªå"
        }
      ],
      "title": "P.willinckii æåçªå\nfrom @comolebi_plants \nèå­èãçµæ§è½ã¡ãã®ã§ããªã¥ã¼ã ãã¦ã³ã\nãããè²¯æ°´èã¯ãã£ã¡ãããæãã\n\n#ããã«jgjs \n#æåçªå \n#æåçªåé¹¿è§è¨ \n#ãã«ã¯ã·ã \n#ãã«ã¯ã·ãã®ããæ®ãã \n#ãã«ã¯ã·ãæ®åå§å¡ä¼ \n#ãã«ã¯ã·ãå¥½ããªäººã¨ç¹ãããã \n#ãã«ã¯ã·ãå¥½ããªäººã¨ç¹ãããã \n#platycerium \n#platyceriumwillinckii \n#willinckii\n\n#ã¸ãµã¯ãæå",
      "creation_timestamp": 1733370778,
      "hashtags": [
        "#ããã«jgjs",
        "#æåçªå",
        "#æåçªåé¹¿è§è¨",
        "#ãã«ã¯ã·ã",
        "#ãã«ã¯ã·ãã®ããæ®ãã",
        "#ãã«ã¯ã·ãæ®åå§å¡ä¼",
        "#ãã«ã¯ã·ãå¥½ããªäººã¨ç¹ãããã",
        "#ãã«ã¯ã·ãå¥½ããªäººã¨ç¹ãããã",
        "#platycerium",
        "#platyceriumwillinckii",
        "#willinckii",
        "#ã¸ãµã¯ãæå"
      ],
      "year": 2024,
      "month": 12,
      "day": 5
    },
    {
      "id": "1733110561-80",
      "media": [
        {
          "uri": "images/posts/202412/469124999_599602525860996_5928925113913269497_n_17959850516836732.jpg",
          "creation_timestamp": 1733110560,
          "alt": "P.coronarium"
        },
        {
          "uri": "images/posts/202412/469114457_1088948302441625_5866195934409721696_n_18051214588974948.jpg",
          "creation_timestamp": 1733110560,
          "alt": "P.coronarium"
        }
      ],
      "title": "P.coronarium \nfrom @katsu_hibino \nãã«ã¯ã·ããæãã\n\n#ãã«ã¯ã·ã \n#ãã«ã¯ã·ãã®ããæ®ãã \n#ãã«ã¯ã·ãå¥½ããªäººã¨ç¹ãããã \n#ãã«ã¯ã·ãå¥½ãã¨ç¹ãããã \n#ãã«ã¯ã·ãã³ã­ããªã¦ã  \n#platyceriumcoronarium\n\n#ã¸ãµã¯ãã³ã­ã",
      "creation_timestamp": 1733110561,
      "hashtags": [
        "#ãã«ã¯ã·ã",
        "#ãã«ã¯ã·ãã®ããæ®ãã",
        "#ãã«ã¯ã·ãå¥½ããªäººã¨ç¹ãããã",
        "#ãã«ã¯ã·ãå¥½ãã¨ç¹ãããã",
        "#ãã«ã¯ã·ãã³ã­ããªã¦ã",
        "#platyceriumcoronarium",
        "#ã¸ãµã¯ãã³ã­ã"
      ],
      "year": 2024,
      "month": 12,
      "day": 2
    },
    {
      "id": "1733064104-81",
      "media": [
        {
          "uri": "images/posts/202412/468885637_920166136357458_2958241953636820955_n_18379915675105702.jpg",
          "creation_timestamp": 1733064103,
          "alt": "P.willinckii winnie"
        },
        {
          "uri": "images/posts/202412/469183174_2525668230961612_8970667691026939890_n_17964760709697014.jpg",
          "creation_timestamp": 1733064103,
          "alt": "P.willinckii winnie"
        },
        {
          "uri": "images/posts/202412/469096093_1226755528581777_3690424181546435172_n_18055923304746471.jpg",
          "creation_timestamp": 1733064103,
          "alt": "P.willinckii winnie"
        }
      ],
      "title": "P.willinckii winnie \nfrom @big_bell.plants_aqua \nèå¢ãããã°ã¡ã³ããã³ã³ãã¹ããæ¿æ¿ã\nãã«ããã¨æµè¡ãããç´æãããã®ã§æ©ãæ¨æ¬æ ªã«ãã¾ãï¼\n\n#ãã«ã¯ã·ã \n#ãã«ã¯ã·ãã®ããæ®ãã \n#ãã«ã¯ã·ãæ¿ä» \n#ãã«ã¯ã·ãã¦ã£ãªã³ã­ã¼ \n#ã¦ã£ãªã³ã­ã¼ \n#willinckii \n#willinckiiå \n#platyceriumwillinckii \n\n#ã¸ãµã¯ãã¦ã£ãã¼",
      "creation_timestamp": 1733064104,
      "hashtags": [
        "#ãã«ã¯ã·ã",
        "#ãã«ã¯ã·ãã®ããæ®ãã",
        "#ãã«ã¯ã·ãæ¿ä»",
        "#ãã«ã¯ã·ãã¦ã£ãªã³ã­ã¼",
        "#ã¦ã£ãªã³ã­ã¼",
        "#willinckii",
        "#willinckiiå",
        "#platyceriumwillinckii",
        "#ã¸ãµã¯ãã¦ã£ãã¼"
      ],
      "year": 2024,
      "month": 12,
      "day": 1
    }
  ]
}